iambic/__init__.py
iambic/plugins/v0_1_0/__init__.py
iambic/plugins/v0_1_0/generic_git_provider/__init__.py
iambic/plugins/v0_1_0/generic_git_provider/aws_lambda_handler.py
iambic/plugins/v0_1_0/generic_git_provider/generic_git_client.py
iambic_plugin_generic_git_provider-0.1.0.dist-info/LICENSE
iambic_plugin_generic_git_provider-0.1.0.dist-info/METADATA
iambic_plugin_generic_git_provider-0.1.0.dist-info/WHEEL
iambic_plugin_generic_git_provider-0.1.0.dist-info/RECORD
