Metadata-Version: 2.1
Name: iambic-plugin-generic-git-provider
Version: 0.1.0
Summary: Run iambic inside a AWS Lambda with generic git provider that supports repository clone via https
License: Apache-2.0
Author: Noq Software
Author-email: hello@noq.dev
Requires-Python: >=3.9,<4.0
Classifier: License :: OSI Approved :: Apache Software License
Classifier: Programming Language :: Python :: 3
Classifier: Programming Language :: Python :: 3.9
Classifier: Programming Language :: Python :: 3.10
Classifier: Programming Language :: Python :: 3.11
Requires-Dist: boto3 (>=1.26.95,<2.0.0)
Requires-Dist: iambic-core (>=0.11.73,<0.12.0)
Requires-Dist: ruamel.yaml (>=0.17.21,<0.18.0)
